acoupi_batdetect2/__init__.py
acoupi_batdetect2/configuration.py
acoupi_batdetect2/model.py
acoupi_batdetect2/program.py
acoupi_batdetect2-0.3.0.dist-info/METADATA
acoupi_batdetect2-0.3.0.dist-info/WHEEL
acoupi_batdetect2-0.3.0.dist-info/licenses/LICENSE.md
acoupi_batdetect2-0.3.0.dist-info/RECORD
