Metadata-Version: 2.3
Name: acoupi-batdetect2
Version: 0.3.0
Summary: An acoupi-compatible BatDetect2 model and program.
Author-email: Aude Vuilliomenet <aude.vuilliomenet.18@ucl.ac.uk>, Santiago Martinez Balvanera <santiago.balvanera.20@ucl.uk.ac>
License: Creative Commons Attribution-NonCommercial 4.0 International
Requires-Python: <3.13,>=3.9
Requires-Dist: acoupi>=0.3.0
Requires-Dist: batdetect2>=1.1.0
Requires-Dist: pydantic-settings>=2.1.0
Requires-Dist: pygments>=2.18.0
